delphi_tree_sitter/__init__.py
delphi_tree_sitter/class_structure.py
delphi_tree_sitter/cli.py
delphi_tree_sitter/demo_utils.py
delphi_tree_sitter/exceptions.py
delphi_tree_sitter/forward_declarations.py
delphi_tree_sitter/helpers.py
delphi_tree_sitter/inheritance.py
delphi_tree_sitter/language.py
delphi_tree_sitter/lookahead.py
delphi_tree_sitter/parser.py
delphi_tree_sitter/query.py
delphi_tree_sitter/tree.py
delphi_tree_sitter/types.py
delphi_tree_sitter/utils.py
delphi_tree_sitter/validation.py
delphi_tree_sitter/wasm.py
tree_sitter_delphi-0.1.0.dist-info/METADATA
tree_sitter_delphi-0.1.0.dist-info/WHEEL
tree_sitter_delphi-0.1.0.dist-info/entry_points.txt
tree_sitter_delphi-0.1.0.dist-info/top_level.txt
tree_sitter_delphi-0.1.0.dist-info/RECORD
