Metadata-Version: 2.4
Name: tree-sitter-delphi
Version: 0.1.0
Summary: Python bindings for tree-sitter parsers with Delphi-inspired architecture
Home-page: https://github.com/adaptsai/delphi-tree-sitter
Author: Your Name
Author-email: AdaptSAI <info@adaptsai.com>
Maintainer-email: AdaptSAI <info@adaptsai.com>
License: Proprietary
Project-URL: Homepage, https://github.com/adaptsai/tree-sitter-delphi
Project-URL: Documentation, https://adapts.wiki.tree-sitter-delphi/
Project-URL: Repository, https://github.com/adaptsai/tree-sitter-delphi.git
Project-URL: Bug Tracker, https://github.com/adaptsai/tree-sitter-delphi/issues
Keywords: tree-sitter,parsing,syntax,ast,compiler,delphi,adaptsai
Classifier: Development Status :: 3 - Alpha
Classifier: Intended Audience :: Developers
Classifier: License :: Other/Proprietary License
Classifier: Operating System :: OS Independent
Classifier: Programming Language :: Python :: 3
Classifier: Programming Language :: Python :: 3.7
Classifier: Programming Language :: Python :: 3.8
Classifier: Programming Language :: Python :: 3.9
Classifier: Programming Language :: Python :: 3.10
Classifier: Programming Language :: Python :: 3.11
Classifier: Programming Language :: Python :: 3.12
Classifier: Topic :: Software Development :: Libraries :: Python Modules
Classifier: Topic :: Text Processing :: Linguistic
Classifier: Topic :: Software Development :: Compilers
Requires-Python: >=3.7
Provides-Extra: dev
Requires-Dist: pytest>=6.0; extra == "dev"
Requires-Dist: pytest-cov; extra == "dev"
Requires-Dist: black; extra == "dev"
Requires-Dist: flake8; extra == "dev"
Requires-Dist: mypy; extra == "dev"
Provides-Extra: docs
Requires-Dist: sphinx; extra == "docs"
Requires-Dist: sphinx-rtd-theme; extra == "docs"
Dynamic: author
Dynamic: home-page
Dynamic: requires-python
